{
  "name": "fxp0TJbbmzn6NEswlk0Y/RmdGpwpVSEyI47zCGMMc/5739e580-997c-4c98-85b3-cc4c9badb2ef.png",
  "bucket": "sol-monks.appspot.com",
  "contentType": "image/png",
  "metageneration": 1,
  "generation": 1636010263256,
  "storageClass": "STANDARD",
  "etag": "someETag",
  "contentDisposition": "inline",
  "contentEncoding": "identity",
  "downloadTokens": [
    "3048c174-0b57-45b4-8db8-a09b10bac25b"
  ],
  "timeCreated": "2021-11-04T07:17:43.255Z",
  "updated": "2021-11-04T07:17:43.257Z",
  "size": 123769,
  "md5Hash": "rByCuHtqq7zG71nlk/8qUg==",
  "crc32c": "879180304"
}