{
  "name": "fxp0TJbbmzn6NEswlk0Y/RmdGpwpVSEyI47zCGMMc/aed9ae97-87cc-4a8d-9706-2cbc869acde5.png",
  "bucket": "sol-monks.appspot.com",
  "contentType": "image/png",
  "metageneration": 1,
  "generation": 1636010138554,
  "storageClass": "STANDARD",
  "etag": "someETag",
  "contentDisposition": "inline",
  "contentEncoding": "identity",
  "downloadTokens": [
    "01c39285-5279-4161-bb9a-ed1de8480696"
  ],
  "timeCreated": "2021-11-04T07:15:38.553Z",
  "updated": "2021-11-04T07:15:38.554Z",
  "size": 57033,
  "md5Hash": "VdWorz0AdM9k4R9K2XG+yg==",
  "crc32c": "2967090412"
}