{
  "name": "fxp0TJbbmzn6NEswlk0Y/RmdGpwpVSEyI47zCGMMc/d347407f-1d5e-4399-85c3-0b999c1cf913.png",
  "bucket": "sol-monks.appspot.com",
  "contentType": "image/png",
  "metageneration": 1,
  "generation": 1636009589172,
  "storageClass": "STANDARD",
  "etag": "someETag",
  "contentDisposition": "inline",
  "contentEncoding": "identity",
  "downloadTokens": [
    "3b70f32c-08b5-480a-87c2-c617e5754f5b"
  ],
  "timeCreated": "2021-11-04T07:06:29.171Z",
  "updated": "2021-11-04T07:06:29.212Z",
  "size": 4794315,
  "md5Hash": "1b5G13IgNKlXqNisQBFjBw==",
  "crc32c": "4119725488"
}