{
  "name": "fxp0TJbbmzn6NEswlk0Y/RmdGpwpVSEyI47zCGMMc/def0324f-c2ed-49c7-bc20-b555b6c1798d.png",
  "bucket": "sol-monks.appspot.com",
  "contentType": "image/png",
  "metageneration": 1,
  "generation": 1636011788407,
  "storageClass": "STANDARD",
  "etag": "someETag",
  "contentDisposition": "inline",
  "contentEncoding": "identity",
  "downloadTokens": [
    "bb2f4446-15af-4dbc-a639-c4da46d57eda"
  ],
  "timeCreated": "2021-11-04T07:43:08.406Z",
  "updated": "2021-11-04T07:43:08.410Z",
  "size": 216500,
  "md5Hash": "rbrs6wR/yC35qv8ARNGipQ==",
  "crc32c": "422442245"
}