{
  "name": "fxp0TJbbmzn6NEswlk0Y/kC5xNQmAAZFRzyBXlE2i/generated/2HJs08qspHuMkXjRGJXh/35.png",
  "bucket": "sol-monks.appspot.com",
  "contentType": "image/png",
  "metageneration": 1,
  "generation": 1636024475032,
  "storageClass": "STANDARD",
  "etag": "someETag",
  "contentDisposition": "inline",
  "contentEncoding": "identity",
  "downloadTokens": [],
  "timeCreated": "2021-11-04T11:14:35.031Z",
  "updated": "2021-11-04T11:14:35.035Z",
  "size": 709973,
  "md5Hash": "X6hOY8ZTNh92pm++jvzBog==",
  "crc32c": "729261660"
}