{
  "name": "fxp0TJbbmzn6NEswlk0Y/kC5xNQmAAZFRzyBXlE2i/44ab621e-d3a3-4b25-acf4-7abd4fa23e5d.png",
  "bucket": "sol-monks.appspot.com",
  "contentType": "image/png",
  "metageneration": 1,
  "generation": 1636022087542,
  "storageClass": "STANDARD",
  "etag": "someETag",
  "contentDisposition": "inline",
  "contentEncoding": "identity",
  "downloadTokens": [
    "af027a1b-86fb-47cc-b2b0-bf2933899662"
  ],
  "timeCreated": "2021-11-04T10:34:47.541Z",
  "updated": "2021-11-04T10:34:47.541Z",
  "size": 3240,
  "md5Hash": "vhx8Z9eUWd2cNJ6cpsP/SA==",
  "crc32c": "817650936"
}