{
  "name": "fxp0TJbbmzn6NEswlk0Y/kC5xNQmAAZFRzyBXlE2i/453d28d3-31d2-4931-ad21-60e3910b81e6.png",
  "bucket": "sol-monks.appspot.com",
  "contentType": "image/png",
  "metageneration": 1,
  "generation": 1636024931202,
  "storageClass": "STANDARD",
  "etag": "someETag",
  "contentDisposition": "inline",
  "contentEncoding": "identity",
  "downloadTokens": [
    "74d32331-2544-420b-a931-f56902e18e26"
  ],
  "timeCreated": "2021-11-04T11:22:11.201Z",
  "updated": "2021-11-04T11:22:11.201Z",
  "size": 5267,
  "md5Hash": "PfKzWwxER+SwJaFDDYdRnA==",
  "crc32c": "1471572649"
}