{
  "name": "fxp0TJbbmzn6NEswlk0Y/kC5xNQmAAZFRzyBXlE2i/9008b128-6f88-444c-8e2d-c7ed18ee6fc2.png",
  "bucket": "sol-monks.appspot.com",
  "contentType": "image/png",
  "metageneration": 1,
  "generation": 1636022086781,
  "storageClass": "STANDARD",
  "etag": "someETag",
  "contentDisposition": "inline",
  "contentEncoding": "identity",
  "downloadTokens": [
    "caacb73b-0a51-4c1b-abe3-6a5d4cef5e9e"
  ],
  "timeCreated": "2021-11-04T10:34:46.780Z",
  "updated": "2021-11-04T10:34:46.780Z",
  "size": 106696,
  "md5Hash": "4coo1r4Gr4KIX3omRPt+DQ==",
  "crc32c": "1584558035"
}